tistory/__init__.py
tistory/api.py
tistory/config/__init__.py
tistory/config/info.py
tistory-0.0.5.dist-info/METADATA
tistory-0.0.5.dist-info/WHEEL
tistory-0.0.5.dist-info/top_level.txt
tistory-0.0.5.dist-info/RECORD
