Metadata-Version: 2.1
Name: tistory
Version: 0.0.5
Summary: Tistory Open API Python Wrapper
Home-page: https://github.com/WooilJeong/tistory
Author: 정우일(Wooil Jeong)
Author-email: wooil@kakao.com
License: MIT
Platform: UNKNOWN
Classifier: Programming Language :: Python :: 3
Classifier: License :: OSI Approved :: MIT License
Classifier: Operating System :: OS Independent
